{
    "commands":
    [
        {
            "protocol": "http",
            "method": "GET",
            "resource": "/Basement_Downstairs.html"
          },
          {
            "protocol": "http",
            "method": "GET",
            "resource": "/Basement_Downstairs.png"
          },
          {
            "protocol": "http",
            "method": "GET",
            "resource": "/Basement_Downstairs.jpg"
          },
          {
            "protocol": "http",
            "method": "GET",
            "resource": "/Basement_Downstairs.svg"
          }
    ]
  }
  